{"chunk_definitions":[{"row":8,"row_count":1,"visible":true,"expansion_state":0,"options":{"engine":"r","label":"unnamed-chunk-1"},"document_id":"771567CC","chunk_id":"c7mq8g7dmjm69","chunk_label":"unnamed-chunk-1"},{"row":16,"row_count":1,"visible":true,"expansion_state":0,"options":{"engine":"r","label":"unnamed-chunk-2"},"document_id":"771567CC","chunk_id":"cb2gu28u7cl2k","chunk_label":"unnamed-chunk-2"},{"row":22,"row_count":1,"visible":true,"expansion_state":0,"options":{"engine":"r","label":"unnamed-chunk-3"},"document_id":"771567CC","chunk_id":"c6xkfisg5rggc","chunk_label":"unnamed-chunk-3"},{"row":31,"row_count":1,"visible":true,"expansion_state":0,"options":{"engine":"r","label":"unnamed-chunk-4"},"document_id":"771567CC","chunk_id":"cynv3mm8jjnms","chunk_label":"unnamed-chunk-4"},{"row":36,"row_count":1,"visible":true,"expansion_state":0,"options":{"engine":"r","label":"unnamed-chunk-5"},"document_id":"771567CC","chunk_id":"cu51h112ovnlm","chunk_label":"unnamed-chunk-5"},{"row":46,"row_count":1,"visible":true,"expansion_state":0,"options":{"engine":"r","label":"unnamed-chunk-6"},"document_id":"771567CC","chunk_id":"ccq1smsv15jw9","chunk_label":"unnamed-chunk-6"},{"row":73,"row_count":1,"visible":true,"expansion_state":0,"options":{"engine":"r","label":"unnamed-chunk-7"},"document_id":"771567CC","chunk_id":"c4ubnrhmwfs5l","chunk_label":"unnamed-chunk-7"},{"row":98,"row_count":1,"visible":true,"expansion_state":0,"options":{"engine":"r","label":"unnamed-chunk-8"},"document_id":"771567CC","chunk_id":"c97edeby8kjlg","chunk_label":"unnamed-chunk-8"},{"row":125,"row_count":1,"visible":true,"expansion_state":0,"options":{"engine":"r","label":"unnamed-chunk-9"},"document_id":"771567CC","chunk_id":"ceobzo8j833kq","chunk_label":"unnamed-chunk-9"}],"doc_write_time":1620817005}