{"chunk_definitions":[{"row":10,"row_count":1,"visible":true,"expansion_state":0,"options":{"engine":"r","label":"unnamed-chunk-5"},"document_id":"89660F2A","chunk_id":"ccbn3egmsov20","chunk_label":"unnamed-chunk-1"},{"row":18,"row_count":1,"visible":true,"expansion_state":0,"options":{"engine":"r","label":"unnamed-chunk-6"},"document_id":"89660F2A","chunk_id":"cww9dz304d474","chunk_label":"unnamed-chunk-2"},{"row":24,"row_count":1,"visible":true,"expansion_state":0,"options":{"engine":"r","label":"unnamed-chunk-7"},"document_id":"89660F2A","chunk_id":"cceuni8gfybo8","chunk_label":"unnamed-chunk-3"},{"row":72,"row_count":1,"visible":true,"expansion_state":0,"options":{"engine":"r","label":"unnamed-chunk-1"},"document_id":"89660F2A","chunk_id":"cl5sqcj6hihra","chunk_label":"unnamed-chunk-4"},{"row":101,"row_count":1,"visible":true,"expansion_state":0,"options":{"engine":"r","label":"unnamed-chunk-3"},"document_id":"89660F2A","chunk_id":"cqtdf3onp7czk","chunk_label":"unnamed-chunk-5"},{"row":122,"row_count":1,"visible":true,"expansion_state":0,"options":{"engine":"r","label":"unnamed-chunk-2"},"document_id":"89660F2A","chunk_id":"c49lshtmfth01","chunk_label":"unnamed-chunk-6"},{"row":231,"row_count":1,"visible":true,"expansion_state":0,"options":{"engine":"r","label":"unnamed-chunk-2"},"document_id":"89660F2A","chunk_id":"c3j5e5dcgb5e5","chunk_label":"unnamed-chunk-11"}],"doc_write_time":1605197360,"chunk_rendered_width":700}